test_queries/__init__.py
test_queries/test_num_queries.py
dj_test_queries-0.3.0.dist-info/AUTHORS.rst
dj_test_queries-0.3.0.dist-info/LICENSE
dj_test_queries-0.3.0.dist-info/METADATA
dj_test_queries-0.3.0.dist-info/WHEEL
dj_test_queries-0.3.0.dist-info/top_level.txt
dj_test_queries-0.3.0.dist-info/RECORD
