Metadata-Version: 2.1
Name: dj-test-queries
Version: 0.3.0
Summary: Extension of assertNumQueries that can record queries that were executed and show the differences in future runs.
Home-page: https://github.com/PetrDlouhy/dj-test-queries
Author: Petr Dlouhý
Author-email: petr.dlouhy@email.cz
License: MIT
Keywords: dj-test-queries
Classifier: Development Status :: 3 - Alpha
Classifier: Framework :: Django :: 1.11
Classifier: Framework :: Django :: 2.1
Classifier: Intended Audience :: Developers
Classifier: License :: OSI Approved :: BSD License
Classifier: Natural Language :: English
Classifier: Programming Language :: Python :: 2
Classifier: Programming Language :: Python :: 2.7
Classifier: Programming Language :: Python :: 3
Classifier: Programming Language :: Python :: 3.5
Classifier: Programming Language :: Python :: 3.6
License-File: LICENSE
License-File: AUTHORS.rst
Requires-Dist: django-debug-toolbar !=4.1.0,>=3.8.1
